.gitignore
.readthedocs.yml
.travis.yml
CHANGELOG.rst
CODE_OF_CONDUCT.rst
CONTRIBUTING.rst
LICENSE
MANIFEST.in
README.rst
mypy.ini
pyproject.toml
setup.cfg
setup.py
tox.ini
./flask_calibrestekje/__init__.py
./flask_calibrestekje/flask_calibrestekje.py
./test/__init__.py
./test/test_version.py
changelog/.git-dont-delete-me
flask_calibrestekje/__init__.py
flask_calibrestekje/flask_calibrestekje.py
flask_calibrestekje.egg-info/PKG-INFO
flask_calibrestekje.egg-info/SOURCES.txt
flask_calibrestekje.egg-info/dependency_links.txt
flask_calibrestekje.egg-info/not-zip-safe
flask_calibrestekje.egg-info/requires.txt
flask_calibrestekje.egg-info/top_level.txt
test/__init__.py
test/test_version.py