Metadata-Version: 2.1
Name: flask-calibrestekje
Version: 0.0.1
Summary: Library prototyping based on Calibre with Flask
Home-page: https://github.com/decentral1se/flask-calibrestekje
Author: decentral1se
Author-email: lukewm@riseup.net
Maintainer: decentral1se
Maintainer-email: lukewm@riseup.net
License: GPLv3
Project-URL: Source Code, https://github.com/decentral1se/flask-calibrestekje
Project-URL: Documentation, https://flask-calibrestekje.readthedocs.io/
Project-URL: Maintainer Support, https://liberapay.come/decentral1se
Platform: UNKNOWN
Classifier: Programming Language :: Python :: 3
Classifier: Programming Language :: Python :: 3.6
Classifier: Programming Language :: Python :: 3.7
Classifier: Programming Language :: Python :: 3.8
Requires-Python: >=3.6
Provides-Extra: docs
Provides-Extra: changelog
